biblestudy/__init__.py
biblestudy/api_bible_client.py
biblestudy/api_interface.py
biblestudy/cache_manager.py
biblestudy/cli.py
biblestudy/config.py.sample
biblestudy/config_loader.py
biblestudy/daily_verse_loader.py
biblestudy/daily_verses.json
biblestudy/esv_api_client.py
biblestudy/hints.py
biblestudy/nlt_api_client.py
biblestudy/notes_manager.py
biblestudy/openai_client.py
biblestudy/rich_ui.py
biblestudy-1.4.2.dist-info/licenses/LICENSE
biblestudy-1.4.2.dist-info/METADATA
biblestudy-1.4.2.dist-info/WHEEL
biblestudy-1.4.2.dist-info/entry_points.txt
biblestudy-1.4.2.dist-info/top_level.txt
biblestudy-1.4.2.dist-info/RECORD
