Metadata-Version: 2.4
Name: biblestudy
Version: 1.4.2
Summary: A text-based Bible study companion for your terminal
Author-email: labrack <labrack@users.noreply.github.com>
License: MIT
Project-URL: Homepage, https://github.com/labrack/biblestudy-cli
Project-URL: Repository, https://github.com/labrack/biblestudy-cli
Project-URL: Issues, https://github.com/labrack/biblestudy-cli/issues
Keywords: bible,study,cli,terminal,scripture,devotional
Classifier: Development Status :: 4 - Beta
Classifier: Environment :: Console
Classifier: Intended Audience :: Religion
Classifier: Operating System :: OS Independent
Classifier: Programming Language :: Python :: 3
Classifier: Programming Language :: Python :: 3.9
Classifier: Programming Language :: Python :: 3.10
Classifier: Programming Language :: Python :: 3.11
Classifier: Programming Language :: Python :: 3.12
Classifier: Topic :: Religion
Classifier: Topic :: Utilities
Requires-Python: >=3.9
License-File: LICENSE
Requires-Dist: openai>=1.0.0
Requires-Dist: requests>=2.31.0
Requires-Dist: urllib3<2
Requires-Dist: rich>=13.7.0
Requires-Dist: beautifulsoup4>=4.12.0
Provides-Extra: dev
Requires-Dist: pytest>=6.0; extra == "dev"
Requires-Dist: pytest-cov; extra == "dev"
Requires-Dist: black; extra == "dev"
Requires-Dist: flake8; extra == "dev"
Dynamic: license-file
